.gitignore
README.rst
pyproject.toml
setup.py
src/pbcmd/__init__.py
src/pbcmd/calc.py
src/pbcmd/cli.py
src/pbcmd/cpush.py
src/pbcmd/csplit.py
src/pbcmd/csv2tex.py
src/pbcmd/git.py
src/pbcmd/hello.py
src/pbcmd/mail.py
src/pbcmd/obscure.py
src/pbcmd/pqcat.py
src/pbcmd/proxy.py
src/pbcmd/pyon2json.py
src/pbcmd/rm_timestamped.py
src/pbcmd/timefmt.py
src/pbcmd.egg-info/PKG-INFO
src/pbcmd.egg-info/SOURCES.txt
src/pbcmd.egg-info/dependency_links.txt
src/pbcmd.egg-info/entry_points.txt
src/pbcmd.egg-info/requires.txt
src/pbcmd.egg-info/top_level.txt