Metadata-Version: 2.1
Name: pbcmd
Version: 7.1
Summary: PB's miscellaneous command line tools.
Author-email: Parantapa Bhattacharya <pb+pypi@parantapa.net>
Project-URL: Homepage, https://github.com/parantapa/pbcmd
Classifier: Programming Language :: Python :: 3
Classifier: License :: OSI Approved :: MIT License
Classifier: Operating System :: OS Independent
Requires-Python: >=3.10
